langchain_mcp_adapters/__init__.py
langchain_mcp_adapters/client.py
langchain_mcp_adapters/prompts.py
langchain_mcp_adapters/resources.py
langchain_mcp_adapters/sessions.py
langchain_mcp_adapters/tools.py
mseep_langchain_mcp_adapters-0.1.2.dist-info/METADATA
mseep_langchain_mcp_adapters-0.1.2.dist-info/WHEEL
mseep_langchain_mcp_adapters-0.1.2.dist-info/entry_points.txt
mseep_langchain_mcp_adapters-0.1.2.dist-info/licenses/LICENSE
mseep_langchain_mcp_adapters-0.1.2.dist-info/RECORD
